{
    "0": {
        "0": {
            "0": {
                "mi_acc": 0.6144756436347962,
                "rmse": 0.6199304819107057,
                "mae": 0.3855243504047394,
                "mi_prec": 0.7880151271820068,
                "mi_rec": 0.6523735046386718,
                "mi_f_b": 0.7141131162643433,
                "mi_auc": 0.5822386210376613,
                "ma_prec": 0.5665104508399963,
                "ma_rec": 0.5822385907173158,
                "ma_f_b": 0.5641358256340028
            },
            "1": {
                "mi_acc": 0.6149943232536317,
                "rmse": 0.6195186138153077,
                "mae": 0.385005670785904,
                "mi_prec": 0.7897512912750244,
                "mi_rec": 0.6524299502372741,
                "mi_f_b": 0.7148672938346863,
                "mi_auc": 0.5827485271811956,
                "ma_prec": 0.5667342066764831,
                "ma_rec": 0.5827485084533692,
                "ma_f_b": 0.5642388224601746
            },
            "2": {
                "mi_acc": 0.621737039089203,
                "rmse": 0.614140009880066,
                "mae": 0.3782629549503327,
                "mi_prec": 0.7906193137168884,
                "mi_rec": 0.658317756652832,
                "mi_f_b": 0.718709409236908,
                "mi_auc": 0.5913787011753191,
                "ma_prec": 0.5749001622200012,
                "ma_rec": 0.591378664970398,
                "ma_f_b": 0.5733916521072389
            },
            "3": {
                "mi_acc": 0.6243303775787354,
                "rmse": 0.6120589137077332,
                "mae": 0.3756695866584778,
                "mi_prec": 0.7923554182052612,
                "mi_rec": 0.6602553248405456,
                "mi_f_b": 0.7205767631530762,
                "mi_auc": 0.5945518439769371,
                "ma_prec": 0.5777011632919311,
                "ma_rec": 0.5945517778396607,
                "ma_f_b": 0.5764037132263184
            },
            "4": {
                "mi_acc": 0.6300357937812806,
                "rmse": 0.6074558258056642,
                "mae": 0.36996420025825505,
                "mi_prec": 0.7958276271820068,
                "mi_rec": 0.6646176099777221,
                "mi_f_b": 0.7245970368385315,
                "mi_auc": 0.6015293956918903,
                "ma_prec": 0.5839476108551025,
                "ma_rec": 0.6015293359756471,
                "ma_f_b": 0.583138918876648
            },
            "5": {
                "mi_acc": 0.6310731530189515,
                "rmse": 0.606615161895752,
                "mae": 0.36892684102058415,
                "mi_prec": 0.7958276271820068,
                "mi_rec": 0.6655771851539611,
                "mi_f_b": 0.7251604199409485,
                "mi_auc": 0.602827011642787,
                "ma_prec": 0.5852362632751464,
                "ma_rec": 0.6028269886970521,
                "ma_f_b": 0.5845733046531678
            },
            "6": {
                "mi_acc": 0.6295171141624452,
                "rmse": 0.607875680923462,
                "mae": 0.3704828500747681,
                "mi_prec": 0.7949596047401428,
                "mi_rec": 0.6643628001213073,
                "mi_f_b": 0.7240830659866333,
                "mi_auc": 0.6009282505935671,
                "ma_prec": 0.5835135698318481,
                "ma_rec": 0.6009281635284425,
                "ma_f_b": 0.5827135205268861
            },
            "7": {
                "mi_acc": 0.6289984345436097,
                "rmse": 0.6082952976226808,
                "mae": 0.37100152969360356,
                "mi_prec": 0.79322350025177,
                "mi_rec": 0.6643320441246032,
                "mi_f_b": 0.7233350872993469,
                "mi_auc": 0.6003803337703768,
                "ma_prec": 0.5832898736000061,
                "ma_rec": 0.6003802776336671,
                "ma_f_b": 0.5825794696807862
            },
            "8": {
                "mi_acc": 0.6310731530189515,
                "rmse": 0.606615161895752,
                "mae": 0.36892684102058415,
                "mi_prec": 0.786279022693634,
                "mi_rec": 0.6681062698364257,
                "mi_f_b": 0.7225843071937561,
                "mi_auc": 0.6033834051974167,
                "ma_prec": 0.5875495791435241,
                "ma_rec": 0.6033833980560304,
                "ma_f_b": 0.5876835942268372
            },
            "9": {
                "mi_acc": 0.6362598896026612,
                "rmse": 0.6023947954177857,
                "mae": 0.3637401342391968,
                "mi_prec": 0.78541100025177,
                "mi_rec": 0.6732890129089355,
                "mi_f_b": 0.7251937389373779,
                "mi_auc": 0.6097701001241631,
                "ma_prec": 0.5942031860351562,
                "ma_rec": 0.6097700357437135,
                "ma_f_b": 0.5949592947959901
            },
            "10": {
                "mi_acc": 0.6372971892356873,
                "rmse": 0.6015472173690797,
                "mae": 0.3627027750015259,
                "mi_prec": 0.7810707092285156,
                "mi_rec": 0.6755245447158813,
                "mi_f_b": 0.724585771560669,
                "mi_auc": 0.611271941787846,
                "ma_prec": 0.5965433835983276,
                "ma_rec": 0.611271893978119,
                "ma_f_b": 0.5976432919502259
            },
            "11": {
                "mi_acc": 0.6445586442947389,
                "rmse": 0.5955809712409974,
                "mae": 0.3554413795471192,
                "mi_prec": 0.7836748957633972,
                "mi_rec": 0.6818834066390991,
                "mi_f_b": 0.7293283939361572,
                "mi_auc": 0.6197984794216316,
                "ma_prec": 0.6049330949783325,
                "ma_rec": 0.6197984576225282,
                "ma_f_b": 0.6065116286277772
            },
            "12": {
                "mi_acc": 0.6533760190010072,
                "rmse": 0.5882562756538392,
                "mae": 0.3466239452362061,
                "mi_prec": 0.7897512912750244,
                "mi_rec": 0.6887934327125549,
                "mi_f_b": 0.735899031162262,
                "mi_auc": 0.6299308572850153,
                "ma_prec": 0.6144145846366882,
                "ma_rec": 0.6299308300018311,
                "ma_f_b": 0.616410529613495
            },
            "13": {
                "mi_acc": 0.652338719367981,
                "rmse": 0.5891226291656495,
                "mae": 0.3476612746715546,
                "mi_prec": 0.7836748957633972,
                "mi_rec": 0.6896647930145263,
                "mi_f_b": 0.733701229095459,
                "mi_auc": 0.6289302652982103,
                "ma_prec": 0.6145980477333068,
                "ma_rec": 0.6289301872253419,
                "ma_f_b": 0.6166977047920228
            },
            "14": {
                "mi_acc": 0.6559694170951844,
                "rmse": 0.5860848188400269,
                "mae": 0.34403057694435124,
                "mi_prec": 0.7871471047401428,
                "mi_rec": 0.6922339916229248,
                "mi_f_b": 0.7366800904273987,
                "mi_auc": 0.6330227712794094,
                "ma_prec": 0.6182671308517456,
                "ma_rec": 0.6330227613449098,
                "ma_f_b": 0.620494043827057
            },
            "15": {
                "mi_acc": 0.6559694170951844,
                "rmse": 0.5860848188400269,
                "mae": 0.34403057694435124,
                "mi_prec": 0.7828068137168884,
                "mi_rec": 0.6936415553092956,
                "mi_f_b": 0.7355294227600098,
                "mi_auc": 0.6331710890077622,
                "ma_prec": 0.6193186163902282,
                "ma_rec": 0.6331710577011109,
                "ma_f_b": 0.621626889705658
            }
        },
        "1": {
            "0": {
                "meta_doa": 0.48670989258360864,
                "pc-er": -0.08786621093750002,
                "rm": 0.012074537296671739
            },
            "1": {
                "meta_doa": 0.48904144975816766,
                "pc-er": -0.06540527343750002,
                "rm": 0.0189828297564425
            },
            "2": {
                "meta_doa": 0.49065534196146987,
                "pc-er": -0.04996337890625002,
                "rm": 0.028093620432409705
            },
            "3": {
                "meta_doa": 0.493084342111624,
                "pc-er": -0.04007568359375002,
                "rm": 0.03676888284388691
            },
            "4": {
                "meta_doa": 0.4955188072109682,
                "pc-er": -0.023413085937500022,
                "rm": 0.051866348111033855
            },
            "5": {
                "meta_doa": 0.49916534105780586,
                "pc-er": 0.03127441406249998,
                "rm": 0.06558840283144807
            },
            "6": {
                "meta_doa": 0.5014692323144163,
                "pc-er": 0.04607543945312498,
                "rm": 0.07846412431225336
            },
            "7": {
                "meta_doa": 0.5044028744148477,
                "pc-er": 0.05620727539062498,
                "rm": 0.09033096964319659
            },
            "8": {
                "meta_doa": 0.5076384381954695,
                "pc-er": 0.025750732421874978,
                "rm": 0.10560259951446244
            },
            "9": {
                "meta_doa": 0.5109360383668387,
                "pc-er": 0.03952941894531248,
                "rm": 0.12069263250873102
            },
            "10": {
                "meta_doa": 0.5157377319441447,
                "pc-er": 0.05135498046874998,
                "rm": 0.1345055029865806
            },
            "11": {
                "meta_doa": 0.5188792252034398,
                "pc-er": 0.06051025390624998,
                "rm": 0.14707408337378186
            },
            "12": {
                "meta_doa": 0.5211996516289696,
                "pc-er": 0.05172119140624998,
                "rm": 0.16133206205509898
            },
            "13": {
                "meta_doa": 0.5242414321474922,
                "pc-er": 0.05681762695312498,
                "rm": 0.17533249149202712
            },
            "14": {
                "meta_doa": 0.526826834406301,
                "pc-er": 0.06322631835937498,
                "rm": 0.18760589829574348
            },
            "15": {
                "meta_doa": 0.5252258056598185,
                "pc-er": 0.07198486328124998,
                "rm": 0.1991151212729021
            }
        }
    },
    "1": {
        "0": {
            "0": {
                "mi_acc": 0.6280370712280274,
                "rmse": 0.6089975595474244,
                "mae": 0.3719629228115082,
                "mi_prec": 0.80279940366745,
                "mi_rec": 0.6640561938285827,
                "mi_f_b": 0.7258347272872925,
                "mi_auc": 0.5962461121322988,
                "ma_prec": 0.5794373273849487,
                "ma_rec": 0.596246099472046,
                "ma_f_b": 0.5740695357322694
            },
            "1": {
                "mi_acc": 0.6316981673240663,
                "rmse": 0.6060380697250367,
                "mae": 0.3683018267154694,
                "mi_prec": 0.80279940366745,
                "mi_rec": 0.6672145843505859,
                "mi_f_b": 0.7277807593345642,
                "mi_auc": 0.6011930823955931,
                "ma_prec": 0.5840065002441406,
                "ma_rec": 0.6011930465698243,
                "ma_f_b": 0.579488492012024
            },
            "2": {
                "mi_acc": 0.6364052653312684,
                "rmse": 0.6022119879722596,
                "mae": 0.36359469890594487,
                "mi_prec": 0.8054171800613403,
                "mi_rec": 0.6706858992576599,
                "mi_f_b": 0.7309533953666687,
                "mi_auc": 0.6074100482334002,
                "ma_prec": 0.5892318606376648,
                "ma_rec": 0.6074100494384767,
                "ma_f_b": 0.5853554368019105
            },
            "3": {
                "mi_acc": 0.6364052653312684,
                "rmse": 0.6022119879722596,
                "mae": 0.36359469890594487,
                "mi_prec": 0.806289792060852,
                "mi_rec": 0.6704753160476684,
                "mi_f_b": 0.731171190738678,
                "mi_auc": 0.6074034406226883,
                "ma_prec": 0.5890154361724853,
                "ma_rec": 0.6074033737182618,
                "ma_f_b": 0.5850071072578431
            },
            "4": {
                "mi_acc": 0.634836232662201,
                "rmse": 0.6034900307655335,
                "mae": 0.36516376137733464,
                "mi_prec": 0.8054171800613403,
                "mi_rec": 0.6693183302879333,
                "mi_f_b": 0.7301134467124939,
                "mi_auc": 0.6053313955568143,
                "ma_prec": 0.5872736692428588,
                "ma_rec": 0.6053313374519349,
                "ma_f_b": 0.5830510020256043
            },
            "5": {
                "mi_acc": 0.6374513268470765,
                "rmse": 0.6013585686683656,
                "mae": 0.36254869699478154,
                "mi_prec": 0.8089075684547424,
                "mi_rec": 0.6707556962966919,
                "mi_f_b": 0.7323822975158691,
                "mi_auc": 0.6087786529546357,
                "ma_prec": 0.5896715641021728,
                "ma_rec": 0.6087785720825196,
                "ma_f_b": 0.5854944348335267
            },
            "6": {
                "mi_acc": 0.6400663614273072,
                "rmse": 0.5992195963859559,
                "mae": 0.35993363261222844,
                "mi_prec": 0.8080350160598755,
                "mi_rec": 0.6732527136802673,
                "mi_f_b": 0.7335703372955322,
                "mi_auc": 0.6122158547963283,
                "ma_prec": 0.5931517601013183,
                "ma_rec": 0.6122158527374268,
                "ma_f_b": 0.5896786212921143
            },
            "7": {
                "mi_acc": 0.6458195209503175,
                "rmse": 0.5944873452186585,
                "mae": 0.3541804730892182,
                "mi_prec": 0.8089075684547424,
                "mi_rec": 0.6781171679496765,
                "mi_f_b": 0.7368938326835632,
                "mi_auc": 0.6196621719103699,
                "ma_prec": 0.600115430355072,
                "ma_rec": 0.6196621417999268,
                "ma_f_b": 0.5977047443389893
            },
            "8": {
                "mi_acc": 0.6463425517082215,
                "rmse": 0.5940553307533265,
                "mae": 0.3536574721336365,
                "mi_prec": 0.8045445680618286,
                "mi_rec": 0.6797092676162719,
                "mi_f_b": 0.7361035943031311,
                "mi_auc": 0.6202460349730354,
                "ma_prec": 0.601850402355194,
                "ma_rec": 0.6202460289001466,
                "ma_f_b": 0.6000900626182557
            },
            "9": {
                "mi_acc": 0.6489575862884522,
                "rmse": 0.5918904900550843,
                "mae": 0.3510424077510834,
                "mi_prec": 0.80279940366745,
                "mi_rec": 0.6825316071510314,
                "mi_f_b": 0.7370991706848145,
                "mi_auc": 0.6235046515833391,
                "ma_prec": 0.605547022819519,
                "ma_rec": 0.6235046148300172,
                "ma_f_b": 0.6044545531272889
            },
            "10": {
                "mi_acc": 0.6541877150535584,
                "rmse": 0.5875373244285584,
                "mae": 0.3458122789859772,
                "mi_prec": 0.8045445680618286,
                "mi_rec": 0.6868367910385131,
                "mi_f_b": 0.740398645401001,
                "mi_auc": 0.6300282849195857,
                "ma_prec": 0.6116415381431579,
                "ma_rec": 0.6300282239913941,
                "ma_f_b": 0.6112340450286866
            },
            "11": {
                "mi_acc": 0.6573257803916932,
                "rmse": 0.5849101901054383,
                "mae": 0.34267421364784245,
                "mi_prec": 0.8054171800613403,
                "mi_rec": 0.6894866347312927,
                "mi_f_b": 0.7423433065414429,
                "mi_auc": 0.63389709380041,
                "ma_prec": 0.6153414964675903,
                "ma_rec": 0.6338970422744752,
                "ma_f_b": 0.61534241437912
            },
            "12": {
                "mi_acc": 0.6641249418258668,
                "rmse": 0.5791778922080995,
                "mae": 0.33587505221366887,
                "mi_prec": 0.8001815676689148,
                "mi_rec": 0.6973812699317932,
                "mi_f_b": 0.7448545098304749,
                "mi_auc": 0.6418554466543642,
                "ma_prec": 0.6251258373260498,
                "ma_rec": 0.6418554544448853,
                "ma_f_b": 0.6264874696731568
            },
            "13": {
                "mi_acc": 0.6625559091567994,
                "rmse": 0.5805056452751161,
                "mae": 0.33744408488273625,
                "mi_prec": 0.794946014881134,
                "mi_rec": 0.6974483847618103,
                "mi_f_b": 0.7426926493644714,
                "mi_auc": 0.639835487951887,
                "ma_prec": 0.6244662523269653,
                "ma_rec": 0.6398354530334474,
                "ma_f_b": 0.6259862542152406
            },
            "14": {
                "mi_acc": 0.6677860379219056,
                "rmse": 0.5760680794715882,
                "mae": 0.33221395611763005,
                "mi_prec": 0.795818567276001,
                "mi_rec": 0.7022316575050354,
                "mi_f_b": 0.7458509802818298,
                "mi_auc": 0.6460019404705419,
                "ma_prec": 0.6307771921157836,
                "ma_rec": 0.6460019111633302,
                "ma_f_b": 0.6328111052513123
            },
            "15": {
                "mi_acc": 0.6719701647758485,
                "rmse": 0.5724937677383424,
                "mae": 0.32802985906600957,
                "mi_prec": 0.7966911792755127,
                "mi_rec": 0.7060440301895141,
                "mi_f_b": 0.7484346628189087,
                "mi_auc": 0.6508871688475124,
                "ma_prec": 0.6357827305793762,
                "ma_rec": 0.6508871078491212,
                "ma_f_b": 0.6381824374198914
            }
        },
        "1": {
            "0": {
                "meta_doa": 0.47721278655582977,
                "pc-er": 0.17855224609374998,
                "rm": 0.04530781032207526
            },
            "1": {
                "meta_doa": 0.47861928594035996,
                "pc-er": 0.18972167968749998,
                "rm": 0.05178394054683105
            },
            "2": {
                "meta_doa": 0.4799676773492412,
                "pc-er": 0.19973144531249998,
                "rm": 0.05842891572764525
            },
            "3": {
                "meta_doa": 0.4818734338538806,
                "pc-er": 0.21083984374999998,
                "rm": 0.06532503912634635
            },
            "4": {
                "meta_doa": 0.4848176136796958,
                "pc-er": 0.22365722656249998,
                "rm": 0.07688029434044752
            },
            "5": {
                "meta_doa": 0.4866410521141622,
                "pc-er": 0.22988281249999998,
                "rm": 0.08858835988016961
            },
            "6": {
                "meta_doa": 0.48944235827091465,
                "pc-er": 0.23684082031249998,
                "rm": 0.09979559266110011
            },
            "7": {
                "meta_doa": 0.4921844189079576,
                "pc-er": 0.24428710937499998,
                "rm": 0.11076019733116332
            },
            "8": {
                "meta_doa": 0.49382649365783227,
                "pc-er": 0.24978027343749998,
                "rm": 0.10828430817167395
            },
            "9": {
                "meta_doa": 0.4979999253538525,
                "pc-er": 0.259423828125,
                "rm": 0.12344232273077155
            },
            "10": {
                "meta_doa": 0.5012698466519983,
                "pc-er": 0.271630859375,
                "rm": 0.1372571328329848
            },
            "11": {
                "meta_doa": 0.5043043091994759,
                "pc-er": 0.281884765625,
                "rm": 0.1496088925792447
            },
            "12": {
                "meta_doa": 0.5067570513524855,
                "pc-er": 0.30361328125,
                "rm": 0.12773608523496438
            },
            "13": {
                "meta_doa": 0.5111406428937173,
                "pc-er": 0.31533203125,
                "rm": 0.1413885921202574
            },
            "14": {
                "meta_doa": 0.5133498483880399,
                "pc-er": 0.330712890625,
                "rm": 0.15412732783438016
            },
            "15": {
                "meta_doa": 0.5147878220478563,
                "pc-er": 0.342431640625,
                "rm": 0.16632724131130255
            }
        }
    },
    "2": {
        "0": {
            "0": {
                "mi_acc": 0.6217297077178956,
                "rmse": 0.6150949358940125,
                "mae": 0.37827025651931767,
                "mi_prec": 0.7776632905006409,
                "mi_rec": 0.6642688632011413,
                "mi_f_b": 0.7164536118507385,
                "mi_auc": 0.5850741015266359,
                "ma_prec": 0.5735355734825134,
                "ma_rec": 0.5850741624832154,
                "ma_f_b": 0.5713292717933656
            },
            "1": {
                "mi_acc": 0.6217297077178956,
                "rmse": 0.6150949358940125,
                "mae": 0.37827025651931767,
                "mi_prec": 0.7760049104690552,
                "mi_rec": 0.6647594690322876,
                "mi_f_b": 0.7160330414772034,
                "mi_auc": 0.5853749629009766,
                "ma_prec": 0.5741248250007629,
                "ma_rec": 0.5853750467300416,
                "ma_f_b": 0.5721060395240785
            },
            "2": {
                "mi_acc": 0.6222529768943788,
                "rmse": 0.6146682262420655,
                "mae": 0.3777469873428345,
                "mi_prec": 0.7751756906509399,
                "mi_rec": 0.665485394001007,
                "mi_f_b": 0.7160998582839966,
                "mi_auc": 0.5862721102533479,
                "ma_prec": 0.57512868642807,
                "ma_rec": 0.586272156238556,
                "ma_f_b": 0.5732879996299745
            },
            "3": {
                "mi_acc": 0.623822844028473,
                "rmse": 0.6133863091468812,
                "mae": 0.3761771202087403,
                "mi_prec": 0.7760049104690552,
                "mi_rec": 0.6666783809661865,
                "mi_f_b": 0.717144250869751,
                "mi_auc": 0.5883576104468113,
                "ma_prec": 0.5769617676734924,
                "ma_rec": 0.5883576631546021,
                "ma_f_b": 0.5752910137176515
            },
            "4": {
                "mi_acc": 0.6316721796989442,
                "rmse": 0.6069361329078675,
                "mae": 0.36832784414291386,
                "mi_prec": 0.780150830745697,
                "mi_rec": 0.6726690053939819,
                "mi_f_b": 0.7223784327507019,
                "mi_auc": 0.5987108360984437,
                "ma_prec": 0.5861268758773803,
                "ma_rec": 0.5987108707427979,
                "ma_f_b": 0.5852756261825562
            },
            "5": {
                "mi_acc": 0.6363817214965821,
                "rmse": 0.6030328035354615,
                "mae": 0.36361824274063115,
                "mi_prec": 0.7818092107772827,
                "mi_rec": 0.6765490293502807,
                "mi_f_b": 0.7253241539001465,
                "mi_auc": 0.6049709543290764,
                "ma_prec": 0.5919206261634826,
                "ma_rec": 0.6049710273742677,
                "ma_f_b": 0.5916027784347535
            },
            "6": {
                "mi_acc": 0.6379515886306764,
                "rmse": 0.6017260313034059,
                "mae": 0.3620484054088593,
                "mi_prec": 0.7776632905006409,
                "mi_rec": 0.6793773293495178,
                "mi_f_b": 0.7251476049423218,
                "mi_auc": 0.607632125957505,
                "ma_prec": 0.5955214023590087,
                "ma_rec": 0.6076321363449098,
                "ma_f_b": 0.5956993460655213
            },
            "7": {
                "mi_acc": 0.6437077283859254,
                "rmse": 0.5969100356101991,
                "mae": 0.3562922358512879,
                "mi_prec": 0.7809800505638123,
                "mi_rec": 0.6837804436683654,
                "mi_f_b": 0.7290973663330078,
                "mi_auc": 0.6149385145531516,
                "ma_prec": 0.6021443724632263,
                "ma_rec": 0.6149385929107667,
                "ma_f_b": 0.6027872323989869
            },
            "8": {
                "mi_acc": 0.6468474626541139,
                "rmse": 0.5942666888237,
                "mae": 0.3531525313854218,
                "mi_prec": 0.782638430595398,
                "mi_rec": 0.6862416386604309,
                "mi_f_b": 0.7312189340591431,
                "mi_auc": 0.6189187159969685,
                "ma_prec": 0.6058104157447814,
                "ma_rec": 0.6189187526702882,
                "ma_f_b": 0.6067057013511659
            },
            "9": {
                "mi_acc": 0.6505104660987855,
                "rmse": 0.5911677241325379,
                "mae": 0.34948952794075017,
                "mi_prec": 0.7842967510223389,
                "mi_rec": 0.6892180562019348,
                "mi_f_b": 0.7336316108703613,
                "mi_auc": 0.6235654103017498,
                "ma_prec": 0.6101856350898742,
                "ma_rec": 0.6235654115676881,
                "ma_f_b": 0.611377513408661
            },
            "10": {
                "mi_acc": 0.653650200366974,
                "rmse": 0.5884984493255616,
                "mae": 0.3463498234748841,
                "mi_prec": 0.7809800505638123,
                "mi_rec": 0.6934635162353515,
                "mi_f_b": 0.7345653772354126,
                "mi_auc": 0.6279191718012316,
                "ma_prec": 0.6156195521354675,
                "ma_rec": 0.6279192328453065,
                "ma_f_b": 0.6171992182731629
            },
            "11": {
                "mi_acc": 0.653650200366974,
                "rmse": 0.5884984493255616,
                "mae": 0.3463498234748841,
                "mi_prec": 0.7818092107772827,
                "mi_rec": 0.6931668043136596,
                "mi_f_b": 0.7347654700279236,
                "mi_auc": 0.627847937770512,
                "ma_prec": 0.615324866771698,
                "ma_rec": 0.6278480052947999,
                "ma_f_b": 0.6168827772140504
            },
            "12": {
                "mi_acc": 0.6541734695434571,
                "rmse": 0.5880524277687074,
                "mae": 0.34582652449607854,
                "mi_prec": 0.782638430595398,
                "mi_rec": 0.6933861494064331,
                "mi_f_b": 0.7352549433708191,
                "mi_auc": 0.6284509285232758,
                "ma_prec": 0.6157394766807556,
                "ma_rec": 0.6284509658813477,
                "ma_f_b": 0.6173172354698182
            },
            "13": {
                "mi_acc": 0.6526036024093629,
                "rmse": 0.5893895983695985,
                "mae": 0.3473963916301728,
                "mi_prec": 0.7793216705322266,
                "mi_rec": 0.6930236339569091,
                "mi_f_b": 0.7335844039916992,
                "mi_auc": 0.626721766853447,
                "ma_prec": 0.6147903323173523,
                "ma_rec": 0.6267218351364137,
                "ma_f_b": 0.6163301825523377
            },
            "14": {
                "mi_acc": 0.6546967387199403,
                "rmse": 0.5876059889793397,
                "mae": 0.345303225517273,
                "mi_prec": 0.7793216705322266,
                "mi_rec": 0.6950985312461853,
                "mi_f_b": 0.7347452640533447,
                "mi_auc": 0.6294030955802186,
                "ma_prec": 0.617627215385437,
                "ma_rec": 0.6294030904769898,
                "ma_f_b": 0.6193216800689698
            },
            "15": {
                "mi_acc": 0.6573132038116456,
                "rmse": 0.5853689074516297,
                "mae": 0.34268682003021245,
                "mi_prec": 0.782638430595398,
                "mi_rec": 0.6964932203292846,
                "mi_f_b": 0.7369980216026306,
                "mi_auc": 0.6324668792938255,
                "ma_prec": 0.6199947714805603,
                "ma_rec": 0.6324668884277345,
                "ma_f_b": 0.6218132734298707
            }
        },
        "1": {
            "0": {
                "meta_doa": 0.5083056840142041,
                "pc-er": -0.18076171875000002,
                "rm": 0.03340923768486115
            },
            "1": {
                "meta_doa": 0.5100061380917934,
                "pc-er": -0.15805664062500002,
                "rm": 0.040388090997932224
            },
            "2": {
                "meta_doa": 0.5114469747903946,
                "pc-er": -0.13925781250000002,
                "rm": 0.04792559171401478
            },
            "3": {
                "meta_doa": 0.51368434973472,
                "pc-er": -0.13101806640625002,
                "rm": 0.07344893220306337
            },
            "4": {
                "meta_doa": 0.5158925221695899,
                "pc-er": -0.08255615234375002,
                "rm": 0.0871900971009742
            },
            "5": {
                "meta_doa": 0.5182323751614181,
                "pc-er": -0.07684936523437502,
                "rm": 0.09954987407388866
            },
            "6": {
                "meta_doa": 0.5202507438357614,
                "pc-er": -0.07015075683593752,
                "rm": 0.09317462591931797
            },
            "7": {
                "meta_doa": 0.5232956044657341,
                "pc-er": -0.06198730468750002,
                "rm": 0.10416044760497584
            },
            "8": {
                "meta_doa": 0.5255815477011984,
                "pc-er": -0.04171218872070315,
                "rm": 0.11901755027635791
            },
            "9": {
                "meta_doa": 0.5277273829817445,
                "pc-er": -0.03130950927734377,
                "rm": 0.13318194340648953
            },
            "10": {
                "meta_doa": 0.5307622329784675,
                "pc-er": 0.019006347656249978,
                "rm": 0.14676615040547386
            },
            "11": {
                "meta_doa": 0.5334688345647162,
                "pc-er": 0.06728515624999998,
                "rm": 0.159213042574118
            },
            "12": {
                "meta_doa": 0.5360016990603419,
                "pc-er": 0.08242187499999998,
                "rm": 0.17278930099887363
            },
            "13": {
                "meta_doa": 0.5389670693587306,
                "pc-er": 0.09536132812499998,
                "rm": 0.1856158304475018
            },
            "14": {
                "meta_doa": 0.5415886631590815,
                "pc-er": 0.10549316406249998,
                "rm": 0.1978742277559678
            },
            "15": {
                "meta_doa": 0.5423671210519875,
                "pc-er": 0.11464843749999998,
                "rm": 0.20917194420315194
            }
        }
    },
    "3": {
        "0": {
            "0": {
                "mi_acc": 0.622530496120453,
                "rmse": 0.615695869922638,
                "mae": 0.3774695277214051,
                "mi_prec": 0.8101266026496887,
                "mi_rec": 0.6542233347892761,
                "mi_f_b": 0.7237613201141357,
                "mi_auc": 0.5901460787309567,
                "ma_prec": 0.566786777973175,
                "ma_rec": 0.590146040916443,
                "ma_f_b": 0.5619646668434144
            },
            "1": {
                "mi_acc": 0.6235630273818971,
                "rmse": 0.6148333907127381,
                "mae": 0.376436996459961,
                "mi_prec": 0.8126391768455505,
                "mi_rec": 0.6544426202774047,
                "mi_f_b": 0.7248969674110413,
                "mi_auc": 0.5915878942888697,
                "ma_prec": 0.5673701286315918,
                "ma_rec": 0.5915878772735597,
                "ma_f_b": 0.562401032447815
            },
            "2": {
                "mi_acc": 0.6235630273818971,
                "rmse": 0.6148333907127381,
                "mae": 0.376436996459961,
                "mi_prec": 0.8126391768455505,
                "mi_rec": 0.6544426202774047,
                "mi_f_b": 0.7248969674110413,
                "mi_auc": 0.5915878942888697,
                "ma_prec": 0.5673701286315918,
                "ma_rec": 0.5915878772735597,
                "ma_f_b": 0.562401032447815
            },
            "3": {
                "mi_acc": 0.6245954990386964,
                "rmse": 0.6139696598052979,
                "mae": 0.3754044950008393,
                "mi_prec": 0.8126391768455505,
                "mi_rec": 0.6553459286689758,
                "mi_f_b": 0.7254509925842285,
                "mi_auc": 0.593015290556788,
                "ma_prec": 0.5687160015106201,
                "ma_rec": 0.5930152893066407,
                "ma_f_b": 0.5639949798583985
            },
            "4": {
                "mi_acc": 0.6235630273818971,
                "rmse": 0.6148333907127381,
                "mae": 0.376436996459961,
                "mi_prec": 0.8067765235900879,
                "mi_rec": 0.6560524225234985,
                "mi_f_b": 0.7235360145568848,
                "mi_auc": 0.591569158011312,
                "ma_prec": 0.5691493868827819,
                "ma_rec": 0.5915691614151002,
                "ma_f_b": 0.5650670886039735
            },
            "5": {
                "mi_acc": 0.6282093882560731,
                "rmse": 0.6109366774559022,
                "mae": 0.37179066538810734,
                "mi_prec": 0.8084515333175659,
                "mi_rec": 0.659708571434021,
                "mi_f_b": 0.7264323830604553,
                "mi_auc": 0.5978717695333657,
                "ma_prec": 0.5746975660324096,
                "ma_rec": 0.59787175655365,
                "ma_f_b": 0.5713924527168275
            },
            "6": {
                "mi_acc": 0.6338882207870484,
                "rmse": 0.6061390399932862,
                "mae": 0.3661117732524872,
                "mi_prec": 0.8151516914367676,
                "mi_rec": 0.6628597497940063,
                "mi_f_b": 0.7310462594032288,
                "mi_auc": 0.6056565946651202,
                "ma_prec": 0.5800664544105529,
                "ma_rec": 0.6056565999984742,
                "ma_f_b": 0.5770798683166505
            },
            "7": {
                "mi_acc": 0.636469578742981,
                "rmse": 0.6039453506469727,
                "mae": 0.363530445098877,
                "mi_prec": 0.8134766817092896,
                "mi_rec": 0.6656652212142944,
                "mi_f_b": 0.7320732474327087,
                "mi_auc": 0.6089743425035303,
                "ma_prec": 0.5839396238327026,
                "ma_rec": 0.608974313735962,
                "ma_f_b": 0.5816924333572389
            },
            "8": {
                "mi_acc": 0.6405996441841126,
                "rmse": 0.6004183053970338,
                "mae": 0.359400349855423,
                "mi_prec": 0.8143141865730286,
                "mi_rec": 0.6691596031188964,
                "mi_f_b": 0.7345240712165833,
                "mi_auc": 0.6143740166584266,
                "ma_prec": 0.5890690207481384,
                "ma_rec": 0.6143740177154542,
                "ma_f_b": 0.5875202775001527
            },
            "9": {
                "mi_acc": 0.6431809425354005,
                "rmse": 0.5982030391693116,
                "mae": 0.3568190515041352,
                "mi_prec": 0.8151516914367676,
                "mi_rec": 0.6712622165679931,
                "mi_f_b": 0.7361317276954651,
                "mi_auc": 0.6177321512480927,
                "ma_prec": 0.5921795487403869,
                "ma_rec": 0.6177321434020997,
                "ma_f_b": 0.5910153150558473
            },
            "10": {
                "mi_acc": 0.6431809425354005,
                "rmse": 0.5982030391693116,
                "mae": 0.3568190515041352,
                "mi_prec": 0.8134766817092896,
                "mi_rec": 0.6717756509780883,
                "mi_f_b": 0.7357566356658936,
                "mi_auc": 0.6176193366515084,
                "ma_prec": 0.5926879167556762,
                "ma_rec": 0.6176193714141847,
                "ma_f_b": 0.5916922450065614
            },
            "11": {
                "mi_acc": 0.6452460050582887,
                "rmse": 0.5964246749877931,
                "mae": 0.354753988981247,
                "mi_prec": 0.8143141865730286,
                "mi_rec": 0.6734175205230712,
                "mi_f_b": 0.7370843887329102,
                "mi_auc": 0.6202902774100918,
                "ma_prec": 0.5951255083084106,
                "ma_rec": 0.6202902555465699,
                "ma_f_b": 0.5944056868553163
            },
            "12": {
                "mi_acc": 0.649376130104065,
                "rmse": 0.5928516149520875,
                "mae": 0.350623893737793,
                "mi_prec": 0.8159892559051514,
                "mi_rec": 0.6767149090766906,
                "mi_f_b": 0.7397459745407104,
                "mi_auc": 0.6255942370184182,
                "ma_prec": 0.6000007510185241,
                "ma_rec": 0.6255942344665528,
                "ma_f_b": 0.5998157620429994
            },
            "13": {
                "mi_acc": 0.6483435988426209,
                "rmse": 0.5937469363212586,
                "mae": 0.3516564249992371,
                "mi_prec": 0.8118016123771667,
                "mi_rec": 0.6770843982696533,
                "mi_f_b": 0.7382414937019348,
                "mi_auc": 0.6239868722907527,
                "ma_prec": 0.5999257683753967,
                "ma_rec": 0.6239868164062501,
                "ma_f_b": 0.5999263286590577
            },
            "14": {
                "mi_acc": 0.6545387268066407,
                "rmse": 0.5883537888526917,
                "mae": 0.34546126723289494,
                "mi_prec": 0.8151516914367676,
                "mi_rec": 0.6818193316459655,
                "mi_f_b": 0.7424420118331909,
                "mi_auc": 0.6318770878530331,
                "ma_prec": 0.6069843888282775,
                "ma_rec": 0.6318770408630372,
                "ma_f_b": 0.6076496601104737
            },
            "15": {
                "mi_acc": 0.6545387268066407,
                "rmse": 0.5883537888526917,
                "mae": 0.34546126723289494,
                "mi_prec": 0.8084515333175659,
                "mi_rec": 0.6840420484542846,
                "mi_f_b": 0.740960955619812,
                "mi_auc": 0.6313354894950651,
                "ma_prec": 0.6090178608894348,
                "ma_rec": 0.631335473060608,
                "ma_f_b": 0.6101041197776795
            }
        },
        "1": {
            "0": {
                "meta_doa": 0.4884125229524561,
                "pc-er": -0.017797851562500022,
                "rm": -0.025369188608445892
            },
            "1": {
                "meta_doa": 0.49023660696840876,
                "pc-er": -0.012030029296875022,
                "rm": -0.016829967182212413
            },
            "2": {
                "meta_doa": 0.4923880033380268,
                "pc-er": -0.006658935546875022,
                "rm": -0.009898221521158934
            },
            "3": {
                "meta_doa": 0.49387767449862996,
                "pc-er": -0.0014232635498047097,
                "rm": -0.00347837933325007
            },
            "4": {
                "meta_doa": 0.4959177627327176,
                "pc-er": 0.015138244628906228,
                "rm": 0.008550717200910274
            },
            "5": {
                "meta_doa": 0.4986569497300617,
                "pc-er": 0.03182373046874998,
                "rm": 0.02111731643368614
            },
            "6": {
                "meta_doa": 0.5011733466402291,
                "pc-er": 0.05608520507812498,
                "rm": 0.032867034338019574
            },
            "7": {
                "meta_doa": 0.5035084953144473,
                "pc-er": 0.03135070800781248,
                "rm": 0.0437017438368969
            },
            "8": {
                "meta_doa": 0.5079963128236231,
                "pc-er": 0.04253540039062498,
                "rm": 0.05945007313845335
            },
            "9": {
                "meta_doa": 0.5121067848817107,
                "pc-er": 0.05516967773437498,
                "rm": 0.07288817567489264
            },
            "10": {
                "meta_doa": 0.5153087143785848,
                "pc-er": 0.06740722656249998,
                "rm": 0.08582568130149432
            },
            "11": {
                "meta_doa": 0.519511013841401,
                "pc-er": 0.07741699218749998,
                "rm": 0.09778513705011233
            },
            "12": {
                "meta_doa": 0.5225179699030074,
                "pc-er": 0.08443603515624998,
                "rm": 0.11230571821781749
            },
            "13": {
                "meta_doa": 0.524843751974112,
                "pc-er": 0.09346923828124998,
                "rm": 0.12598509829928478
            },
            "14": {
                "meta_doa": 0.5279250641362412,
                "pc-er": 0.10231933593749998,
                "rm": 0.13909094144872386
            },
            "15": {
                "meta_doa": 0.5304318478647478,
                "pc-er": 0.15163574218749998,
                "rm": 0.15109103649869654
            }
        }
    },
    "4": {
        "0": {
            "0": {
                "mi_acc": 0.630247986316681,
                "rmse": 0.6081750750541688,
                "mae": 0.36975197792053227,
                "mi_prec": 0.8067304491996765,
                "mi_rec": 0.661567997932434,
                "mi_f_b": 0.7276062369346619,
                "mi_auc": 0.5977901058057044,
                "ma_prec": 0.5771707415580749,
                "ma_rec": 0.5977901577949525,
                "ma_f_b": 0.5754212498664857
            },
            "1": {
                "mi_acc": 0.6307645201683045,
                "rmse": 0.6077484250068665,
                "mae": 0.36923544406890874,
                "mi_prec": 0.8058971166610718,
                "mi_rec": 0.6622770547866821,
                "mi_f_b": 0.7276788949966431,
                "mi_auc": 0.5985614273698353,
                "ma_prec": 0.5781127333641052,
                "ma_rec": 0.5985615015029908,
                "ma_f_b": 0.5765508174896241
            },
            "2": {
                "mi_acc": 0.6312810540199281,
                "rmse": 0.6073214769363404,
                "mae": 0.3687189102172852,
                "mi_prec": 0.8058971166610718,
                "mi_rec": 0.6627475142478942,
                "mi_f_b": 0.7279567122459412,
                "mi_auc": 0.5992625690120167,
                "ma_prec": 0.5787921071052551,
                "ma_rec": 0.599262571334839,
                "ma_f_b": 0.5773209095001222
            },
            "3": {
                "mi_acc": 0.630247986316681,
                "rmse": 0.6081750750541688,
                "mae": 0.36975197792053227,
                "mi_prec": 0.8017304539680481,
                "mi_rec": 0.6630138278007507,
                "mi_f_b": 0.7263708114624023,
                "mi_auc": 0.5982130925300578,
                "ma_prec": 0.5787468075752258,
                "ma_rec": 0.5982131719589234,
                "ma_f_b": 0.5775475263595582
            },
            "4": {
                "mi_acc": 0.6323141217231751,
                "rmse": 0.6064667463302613,
                "mae": 0.3676858723163605,
                "mi_prec": 0.8008971214294434,
                "mi_rec": 0.6651603698730468,
                "mi_f_b": 0.7272789478302002,
                "mi_auc": 0.6010572807082403,
                "ma_prec": 0.5817269206047058,
                "ma_rec": 0.6010573267936707,
                "ma_f_b": 0.58094379901886
            },
            "5": {
                "mi_acc": 0.634896731376648,
                "rmse": 0.6043246150016786,
                "mae": 0.36510323286056523,
                "mi_prec": 0.8025637865066528,
                "mi_rec": 0.6670532345771789,
                "mi_f_b": 0.729089081287384,
                "mi_auc": 0.6043663211189908,
                "ma_prec": 0.5845982551574707,
                "ma_rec": 0.6043663382530213,
                "ma_f_b": 0.5840574264526368
            },
            "6": {
                "mi_acc": 0.6359297990798951,
                "rmse": 0.6034655928611756,
                "mae": 0.36407016515731816,
                "mi_prec": 0.7983971238136292,
                "mi_rec": 0.6692794680595398,
                "mi_f_b": 0.7286202907562256,
                "mi_auc": 0.6060387355631417,
                "ma_prec": 0.5872703909873962,
                "ma_rec": 0.606038784980774,
                "ma_f_b": 0.5872382879257203
            },
            "7": {
                "mi_acc": 0.6385124683380128,
                "rmse": 0.6013126730918885,
                "mae": 0.36148752570152287,
                "mi_prec": 0.7942304611206055,
                "mi_rec": 0.6730182886123657,
                "mi_f_b": 0.7289949655532837,
                "mi_auc": 0.6097093380321993,
                "ma_prec": 0.5919805288314819,
                "ma_rec": 0.6097093582153321,
                "ma_f_b": 0.5925770163536073
            },
            "8": {
                "mi_acc": 0.6436777472496034,
                "rmse": 0.5969834089279176,
                "mae": 0.3563222169876099,
                "mi_prec": 0.7908971309661865,
                "mi_rec": 0.6790750741958618,
                "mi_f_b": 0.7310079336166382,
                "mi_auc": 0.616534157229146,
                "ma_prec": 0.5998247385025024,
                "ma_rec": 0.6165342092514039,
                "ma_f_b": 0.6011425018310548
            },
            "9": {
                "mi_acc": 0.6478099584579469,
                "rmse": 0.5934971928596497,
                "mae": 0.3521900057792664,
                "mi_prec": 0.7942304611206055,
                "mi_rec": 0.6819990396499633,
                "mi_f_b": 0.734123170375824,
                "mi_auc": 0.621517272293803,
                "ma_prec": 0.6042087793350219,
                "ma_rec": 0.6215172767639161,
                "ma_f_b": 0.605767583847046
            },
            "10": {
                "mi_acc": 0.6524587631225587,
                "rmse": 0.5895504713058473,
                "mae": 0.347541230916977,
                "mi_prec": 0.7950637936592102,
                "mi_rec": 0.6862905144691467,
                "mi_f_b": 0.7369179725646973,
                "mi_auc": 0.6272545391776944,
                "ma_prec": 0.6100602269172668,
                "ma_rec": 0.6272545814514161,
                "ma_f_b": 0.61198148727417
            },
            "11": {
                "mi_acc": 0.6565909743309022,
                "rmse": 0.5860198497772218,
                "mae": 0.34340901970863347,
                "mi_prec": 0.7983971238136292,
                "mi_rec": 0.6892295002937316,
                "mi_f_b": 0.7400417327880859,
                "mi_auc": 0.6322023077621749,
                "ma_prec": 0.6144442677497863,
                "ma_rec": 0.6322023630142213,
                "ma_f_b": 0.6165944695472718
            },
            "12": {
                "mi_acc": 0.6555579066276551,
                "rmse": 0.5869045019149781,
                "mae": 0.34444205760955815,
                "mi_prec": 0.7958971261978149,
                "mi_rec": 0.6890784621238708,
                "mi_f_b": 0.7388570308685303,
                "mi_auc": 0.6310319336686004,
                "ma_prec": 0.6138736128807067,
                "ma_rec": 0.6310319662094117,
                "ma_f_b": 0.6160061717033387
            },
            "13": {
                "mi_acc": 0.6633058547973634,
                "rmse": 0.5802365303039552,
                "mae": 0.3366941392421723,
                "mi_prec": 0.8000637888908386,
                "mi_rec": 0.695360255241394,
                "mi_f_b": 0.7442283034324646,
                "mi_auc": 0.6403168133340896,
                "ma_prec": 0.6227504134178161,
                "ma_rec": 0.6403168201446534,
                "ma_f_b": 0.6253256559371949
            },
            "14": {
                "mi_acc": 0.6700207352638246,
                "rmse": 0.5743947386741639,
                "mae": 0.3299792587757111,
                "mi_prec": 0.8033971190452576,
                "mi_rec": 0.7009462833404541,
                "mi_f_b": 0.7488353848457336,
                "mi_auc": 0.6483006070618315,
                "ma_prec": 0.6305312037467956,
                "ma_rec": 0.6483006238937379,
                "ma_f_b": 0.6334582328796388
            },
            "15": {
                "mi_acc": 0.6700207352638246,
                "rmse": 0.5743947386741639,
                "mae": 0.3299792587757111,
                "mi_prec": 0.8017304539680481,
                "mi_rec": 0.7015731453895568,
                "mi_f_b": 0.7484444975852966,
                "mi_auc": 0.6483191413763129,
                "ma_prec": 0.6310566186904907,
                "ma_rec": 0.648319160938263,
                "ma_f_b": 0.6339816808700562
            }
        },
        "1": {
            "0": {
                "meta_doa": 0.4765601060854916,
                "pc-er": -0.05152740478515627,
                "rm": 0.03772760885303106
            },
            "1": {
                "meta_doa": 0.47821424519892575,
                "pc-er": -0.03607788085937502,
                "rm": 0.04606867097663109
            },
            "2": {
                "meta_doa": 0.47952487416595524,
                "pc-er": -0.017752075195312522,
                "rm": 0.054133250715274805
            },
            "3": {
                "meta_doa": 0.4802001831665015,
                "pc-er": -0.0011047363281250222,
                "rm": 0.06167039493937726
            },
            "4": {
                "meta_doa": 0.4837242497531402,
                "pc-er": 0.03920898437499998,
                "rm": 0.07590161895106623
            },
            "5": {
                "meta_doa": 0.4869080422032206,
                "pc-er": 0.06905517578124998,
                "rm": 0.08979008574844288
            },
            "6": {
                "meta_doa": 0.4893095956742226,
                "pc-er": 0.11269531249999998,
                "rm": 0.10334066000576142
            },
            "7": {
                "meta_doa": 0.492244977937482,
                "pc-er": 0.14248046874999998,
                "rm": 0.11595859899863986
            },
            "8": {
                "meta_doa": 0.49487967935407884,
                "pc-er": 0.16249999999999998,
                "rm": 0.1330545968765749
            },
            "9": {
                "meta_doa": 0.49885499198126126,
                "pc-er": 0.23708496093749998,
                "rm": 0.14848908610942085
            },
            "10": {
                "meta_doa": 0.5018501057395812,
                "pc-er": 0.2563720703125,
                "rm": 0.16264453867588174
            },
            "11": {
                "meta_doa": 0.505653697182723,
                "pc-er": 0.2695556640625,
                "rm": 0.1762196175172201
            },
            "12": {
                "meta_doa": 0.5091585240399221,
                "pc-er": 0.2839599609375,
                "rm": 0.19291351482724167
            },
            "13": {
                "meta_doa": 0.511678376430543,
                "pc-er": 0.2964111328125,
                "rm": 0.2064411213811958
            },
            "14": {
                "meta_doa": 0.5144426379428075,
                "pc-er": 0.3034912109375,
                "rm": 0.21899862695939393
            },
            "15": {
                "meta_doa": 0.5163008923732966,
                "pc-er": 0.3105712890625,
                "rm": 0.2303725938221936
            }
        }
    }
}