{
    "0": {
        "step": 0,
        "metric": "ma_f_b",
        "mean": 0.5704640269279481,
        "std": 0.0059997820961099155,
        "n": 5,
        "type": "predictive"
    },
    "1": {
        "step": 0,
        "metric": "ma_prec",
        "mean": 0.5735792994499207,
        "std": 0.005865855402203393,
        "n": 5,
        "type": "predictive"
    },
    "2": {
        "step": 0,
        "metric": "ma_rec",
        "mean": 0.591160809993744,
        "std": 0.006195560237363775,
        "n": 5,
        "type": "predictive"
    },
    "3": {
        "step": 0,
        "metric": "mae",
        "mean": 0.3759684562683106,
        "std": 0.005773618158765585,
        "n": 5,
        "type": "predictive"
    },
    "4": {
        "step": 0,
        "metric": "meta_doa",
        "mean": 0.4877433738993181,
        "std": 0.011409766395254315,
        "n": 5,
        "type": "interpretability"
    },
    "5": {
        "step": 0,
        "metric": "mi_acc",
        "mean": 0.6240315318107605,
        "std": 0.005773617171613119,
        "n": 5,
        "type": "predictive"
    },
    "6": {
        "step": 0,
        "metric": "mi_auc",
        "mean": 0.5911608091143569,
        "std": 0.006195561569236139,
        "n": 5,
        "type": "predictive"
    },
    "7": {
        "step": 0,
        "metric": "mi_f_b",
        "mean": 0.7217938899993896,
        "std": 0.005130989601730128,
        "n": 5,
        "type": "predictive"
    },
    "8": {
        "step": 0,
        "metric": "mi_prec",
        "mean": 0.7967085003852844,
        "std": 0.011263373151196028,
        "n": 5,
        "type": "predictive"
    },
    "9": {
        "step": 0,
        "metric": "mi_rec",
        "mean": 0.659926974773407,
        "std": 0.005532714244857072,
        "n": 5,
        "type": "predictive"
    },
    "10": {
        "step": 0,
        "metric": "pc-er",
        "mean": -0.027944946289062522,
        "std": 0.11933165306853785,
        "n": 5,
        "type": "interpretability"
    },
    "11": {
        "step": 0,
        "metric": "rm",
        "mean": 0.02177615224176338,
        "std": 0.02571255484558806,
        "n": 5,
        "type": "interpretability"
    },
    "12": {
        "step": 0,
        "metric": "rmse",
        "mean": 0.6130643248558045,
        "std": 0.00460287784992786,
        "n": 5,
        "type": "predictive"
    },
    "13": {
        "step": 1,
        "metric": "ma_f_b",
        "mean": 0.5722131967544557,
        "std": 0.006905710117840356,
        "n": 5,
        "type": "predictive"
    },
    "14": {
        "step": 1,
        "metric": "ma_prec",
        "mean": 0.5751356363296509,
        "std": 0.006796149038644333,
        "n": 5,
        "type": "predictive"
    },
    "15": {
        "step": 1,
        "metric": "ma_rec",
        "mean": 0.592930805683136,
        "std": 0.007639340894083246,
        "n": 5,
        "type": "predictive"
    },
    "16": {
        "step": 1,
        "metric": "mae",
        "mean": 0.37461903095245364,
        "std": 0.006069569708610665,
        "n": 5,
        "type": "predictive"
    },
    "17": {
        "step": 1,
        "metric": "meta_doa",
        "mean": 0.4900253329575765,
        "std": 0.011319140012211529,
        "n": 5,
        "type": "interpretability"
    },
    "18": {
        "step": 1,
        "metric": "mi_acc",
        "mean": 0.6253809571266176,
        "std": 0.006069567756885018,
        "n": 5,
        "type": "predictive"
    },
    "19": {
        "step": 1,
        "metric": "mi_auc",
        "mean": 0.5929307817238826,
        "std": 0.00763935521532155,
        "n": 5,
        "type": "predictive"
    },
    "20": {
        "step": 1,
        "metric": "mi_f_b",
        "mean": 0.7226653814315795,
        "std": 0.005430804060944355,
        "n": 5,
        "type": "predictive"
    },
    "21": {
        "step": 1,
        "metric": "mi_prec",
        "mean": 0.7972561478614807,
        "std": 0.011899053550703208,
        "n": 5,
        "type": "predictive"
    },
    "22": {
        "step": 1,
        "metric": "mi_rec",
        "mean": 0.66100594997406,
        "std": 0.005476900226017722,
        "n": 5,
        "type": "predictive"
    },
    "23": {
        "step": 1,
        "metric": "pc-er",
        "mean": -0.008575439453125023,
        "std": 0.11522184142147186,
        "n": 5,
        "type": "interpretability"
    },
    "24": {
        "step": 1,
        "metric": "rm",
        "mean": 0.03039801116748706,
        "std": 0.025035734927852826,
        "n": 5,
        "type": "interpretability"
    },
    "25": {
        "step": 1,
        "metric": "rmse",
        "mean": 0.6119786977767945,
        "std": 0.0050567376348324995,
        "n": 5,
        "type": "predictive"
    },
    "26": {
        "step": 2,
        "metric": "ma_f_b",
        "mean": 0.5762946248054506,
        "std": 0.0067718780453970145,
        "n": 5,
        "type": "predictive"
    },
    "27": {
        "step": 2,
        "metric": "ma_prec",
        "mean": 0.5788790702819824,
        "std": 0.0065171005179223175,
        "n": 5,
        "type": "predictive"
    },
    "28": {
        "step": 2,
        "metric": "ma_rec",
        "mean": 0.5973344087600709,
        "std": 0.0068453043579991815,
        "n": 5,
        "type": "predictive"
    },
    "29": {
        "step": 2,
        "metric": "mae",
        "mean": 0.37118728756904606,
        "std": 0.005141790864508076,
        "n": 5,
        "type": "predictive"
    },
    "30": {
        "step": 2,
        "metric": "meta_doa",
        "mean": 0.4917506103198983,
        "std": 0.011767561226249683,
        "n": 5,
        "type": "interpretability"
    },
    "31": {
        "step": 2,
        "metric": "mi_acc",
        "mean": 0.6288127064704896,
        "std": 0.0051417908827836685,
        "n": 5,
        "type": "predictive"
    },
    "32": {
        "step": 2,
        "metric": "mi_auc",
        "mean": 0.59733442320371,
        "std": 0.006845324275103199,
        "n": 5,
        "type": "predictive"
    },
    "33": {
        "step": 2,
        "metric": "mi_f_b",
        "mean": 0.7250600576400756,
        "std": 0.004712043953638395,
        "n": 5,
        "type": "predictive"
    },
    "34": {
        "step": 2,
        "metric": "mi_prec",
        "mean": 0.7994648098945618,
        "std": 0.011001084466744589,
        "n": 5,
        "type": "predictive"
    },
    "35": {
        "step": 2,
        "metric": "mi_rec",
        "mean": 0.6635030746459961,
        "std": 0.00496643760844033,
        "n": 5,
        "type": "predictive"
    },
    "36": {
        "step": 2,
        "metric": "pc-er",
        "mean": 0.0075874328613281024,
        "std": 0.11370075984771404,
        "n": 5,
        "type": "interpretability"
    },
    "37": {
        "step": 2,
        "metric": "rm",
        "mean": 0.042711841624898585,
        "std": 0.027365211151346682,
        "n": 5,
        "type": "interpretability"
    },
    "38": {
        "step": 2,
        "metric": "rmse",
        "mean": 0.6091892838478089,
        "std": 0.004527998926079332,
        "n": 5,
        "type": "predictive"
    },
    "39": {
        "step": 3,
        "metric": "ma_f_b",
        "mean": 0.5788639068603516,
        "std": 0.005992942910869712,
        "n": 5,
        "type": "predictive"
    },
    "40": {
        "step": 3,
        "metric": "ma_prec",
        "mean": 0.5811550617218018,
        "std": 0.005771451846775357,
        "n": 5,
        "type": "predictive"
    },
    "41": {
        "step": 3,
        "metric": "ma_rec",
        "mean": 0.5996974468231202,
        "std": 0.0049366674167223455,
        "n": 5,
        "type": "predictive"
    },
    "42": {
        "step": 3,
        "metric": "mae",
        "mean": 0.3695166110992432,
        "std": 0.004349764444561586,
        "n": 5,
        "type": "predictive"
    },
    "43": {
        "step": 3,
        "metric": "meta_doa",
        "mean": 0.4936085532784946,
        "std": 0.011782192368288693,
        "n": 5,
        "type": "interpretability"
    },
    "44": {
        "step": 3,
        "metric": "mi_acc",
        "mean": 0.630483388900757,
        "std": 0.004349777182397279,
        "n": 5,
        "type": "predictive"
    },
    "45": {
        "step": 3,
        "metric": "mi_auc",
        "mean": 0.5996974489690831,
        "std": 0.004936695265045204,
        "n": 5,
        "type": "predictive"
    },
    "46": {
        "step": 3,
        "metric": "mi_f_b",
        "mean": 0.7259056210517884,
        "std": 0.004143291909122031,
        "n": 5,
        "type": "predictive"
    },
    "47": {
        "step": 3,
        "metric": "mi_prec",
        "mean": 0.7993061542510986,
        "std": 0.010943574490604221,
        "n": 5,
        "type": "predictive"
    },
    "48": {
        "step": 3,
        "metric": "mi_rec",
        "mean": 0.665074622631073,
        "std": 0.005187137300588522,
        "n": 5,
        "type": "predictive"
    },
    "49": {
        "step": 3,
        "metric": "pc-er",
        "mean": 0.020630645751953103,
        "std": 0.11583748625990392,
        "n": 5,
        "type": "interpretability"
    },
    "50": {
        "step": 3,
        "metric": "rm",
        "mean": 0.051093281030496006,
        "std": 0.027395480659051605,
        "n": 5,
        "type": "interpretability"
    },
    "51": {
        "step": 3,
        "metric": "rmse",
        "mean": 0.6078144311904908,
        "std": 0.0038488186780122964,
        "n": 5,
        "type": "predictive"
    },
    "52": {
        "step": 4,
        "metric": "ma_f_b",
        "mean": 0.5817584872245789,
        "std": 0.005833870068897788,
        "n": 5,
        "type": "predictive"
    },
    "53": {
        "step": 4,
        "metric": "ma_prec",
        "mean": 0.5837149858474732,
        "std": 0.005734906377169949,
        "n": 5,
        "type": "predictive"
    },
    "54": {
        "step": 4,
        "metric": "ma_rec",
        "mean": 0.6022931456565858,
        "std": 0.004776176885517999,
        "n": 5,
        "type": "predictive"
    },
    "55": {
        "step": 4,
        "metric": "mae",
        "mean": 0.36753797531127935,
        "std": 0.004471331292593521,
        "n": 5,
        "type": "predictive"
    },
    "56": {
        "step": 4,
        "metric": "meta_doa",
        "mean": 0.49661391570316643,
        "std": 0.011311919666108209,
        "n": 5,
        "type": "interpretability"
    },
    "57": {
        "step": 4,
        "metric": "mi_acc",
        "mean": 0.6324620246887208,
        "std": 0.004471331921872213,
        "n": 5,
        "type": "predictive"
    },
    "58": {
        "step": 4,
        "metric": "mi_auc",
        "mean": 0.6022931506514538,
        "std": 0.004776169992440049,
        "n": 5,
        "type": "predictive"
    },
    "59": {
        "step": 4,
        "metric": "mi_f_b",
        "mean": 0.7270414710044861,
        "std": 0.0038022162926774315,
        "n": 5,
        "type": "predictive"
    },
    "60": {
        "step": 4,
        "metric": "mi_prec",
        "mean": 0.7995035171508789,
        "std": 0.00942639110071744,
        "n": 5,
        "type": "predictive"
    },
    "61": {
        "step": 4,
        "metric": "mi_rec",
        "mean": 0.666841721534729,
        "std": 0.005356010094823186,
        "n": 5,
        "type": "predictive"
    },
    "62": {
        "step": 4,
        "metric": "pc-er",
        "mean": 0.05320129394531248,
        "std": 0.10334935420124755,
        "n": 5,
        "type": "interpretability"
    },
    "63": {
        "step": 4,
        "metric": "rm",
        "mean": 0.06665273305686992,
        "std": 0.027400982287921746,
        "n": 5,
        "type": "interpretability"
    },
    "64": {
        "step": 4,
        "metric": "rmse",
        "mean": 0.6061829566955568,
        "std": 0.003933840978935627,
        "n": 5,
        "type": "predictive"
    },
    "65": {
        "step": 5,
        "metric": "ma_f_b",
        "mean": 0.5877400040626527,
        "std": 0.006114991263463751,
        "n": 5,
        "type": "predictive"
    },
    "66": {
        "step": 5,
        "metric": "ma_prec",
        "mean": 0.5891042947769165,
        "std": 0.0054411269443879005,
        "n": 5,
        "type": "predictive"
    },
    "67": {
        "step": 5,
        "metric": "ma_rec",
        "mean": 0.6079660892486574,
        "std": 0.0048980490752859596,
        "n": 5,
        "type": "predictive"
    },
    "68": {
        "step": 5,
        "metric": "mae",
        "mean": 0.36318818330764774,
        "std": 0.004514486855016831,
        "n": 5,
        "type": "predictive"
    },
    "69": {
        "step": 5,
        "metric": "meta_doa",
        "mean": 0.4995037973975431,
        "std": 0.011121012753606305,
        "n": 5,
        "type": "interpretability"
    },
    "70": {
        "step": 5,
        "metric": "mi_acc",
        "mean": 0.6368118047714234,
        "std": 0.004514473807218635,
        "n": 5,
        "type": "predictive"
    },
    "71": {
        "step": 5,
        "metric": "mi_auc",
        "mean": 0.6079660960096749,
        "std": 0.00489802344612409,
        "n": 5,
        "type": "predictive"
    },
    "72": {
        "step": 5,
        "metric": "mi_f_b",
        "mean": 0.7296656966209412,
        "std": 0.003805638086473106,
        "n": 5,
        "type": "predictive"
    },
    "73": {
        "step": 5,
        "metric": "mi_prec",
        "mean": 0.8005276799201966,
        "std": 0.010118696434263025,
        "n": 5,
        "type": "predictive"
    },
    "74": {
        "step": 5,
        "metric": "mi_rec",
        "mean": 0.6705750703811646,
        "std": 0.005146066125018567,
        "n": 5,
        "type": "predictive"
    },
    "75": {
        "step": 5,
        "metric": "pc-er",
        "mean": 0.07202072143554686,
        "std": 0.10626474351172727,
        "n": 5,
        "type": "interpretability"
    },
    "76": {
        "step": 5,
        "metric": "rm",
        "mean": 0.07696916875058643,
        "std": 0.024886140293167384,
        "n": 5,
        "type": "interpretability"
    },
    "77": {
        "step": 5,
        "metric": "rmse",
        "mean": 0.6025694608688356,
        "std": 0.0038410440328445926,
        "n": 5,
        "type": "predictive"
    },
    "78": {
        "step": 6,
        "metric": "ma_f_b",
        "mean": 0.5914683103561402,
        "std": 0.0058137931753878425,
        "n": 5,
        "type": "predictive"
    },
    "79": {
        "step": 6,
        "metric": "ma_prec",
        "mean": 0.5922454953193664,
        "std": 0.005711553913660196,
        "n": 5,
        "type": "predictive"
    },
    "80": {
        "step": 6,
        "metric": "ma_rec",
        "mean": 0.610593342781067,
        "std": 0.005140953604991727,
        "n": 5,
        "type": "predictive"
    },
    "81": {
        "step": 6,
        "metric": "mae",
        "mean": 0.3613084554672242,
        "std": 0.004739966674534992,
        "n": 5,
        "type": "predictive"
    },
    "82": {
        "step": 6,
        "metric": "meta_doa",
        "mean": 0.5021272293360356,
        "std": 0.010975682006946213,
        "n": 5,
        "type": "interpretability"
    },
    "83": {
        "step": 6,
        "metric": "mi_acc",
        "mean": 0.638691544532776,
        "std": 0.004739973664835459,
        "n": 5,
        "type": "predictive"
    },
    "84": {
        "step": 6,
        "metric": "mi_auc",
        "mean": 0.6105933547295933,
        "std": 0.005140931858258928,
        "n": 5,
        "type": "predictive"
    },
    "85": {
        "step": 6,
        "metric": "mi_f_b",
        "mean": 0.7300918221473693,
        "std": 0.003844931653864623,
        "n": 5,
        "type": "predictive"
    },
    "86": {
        "step": 6,
        "metric": "mi_prec",
        "mean": 0.7981576681137085,
        "std": 0.010057202008500613,
        "n": 5,
        "type": "predictive"
    },
    "87": {
        "step": 6,
        "metric": "mi_rec",
        "mean": 0.6729529500007629,
        "std": 0.005768858803178827,
        "n": 5,
        "type": "predictive"
    },
    "88": {
        "step": 6,
        "metric": "pc-er",
        "mean": 0.09649658203124997,
        "std": 0.10591789683136071,
        "n": 5,
        "type": "interpretability"
    },
    "89": {
        "step": 6,
        "metric": "rm",
        "mean": 0.09009178320950442,
        "std": 0.024965262054095598,
        "n": 5,
        "type": "interpretability"
    },
    "90": {
        "step": 6,
        "metric": "rmse",
        "mean": 0.6009950518608094,
        "std": 0.003852529714379629,
        "n": 5,
        "type": "predictive"
    },
    "91": {
        "step": 7,
        "metric": "ma_f_b",
        "mean": 0.5959648609161378,
        "std": 0.00862080109994452,
        "n": 5,
        "type": "predictive"
    },
    "92": {
        "step": 7,
        "metric": "ma_prec",
        "mean": 0.5962491035461426,
        "std": 0.008015250068311996,
        "n": 5,
        "type": "predictive"
    },
    "93": {
        "step": 7,
        "metric": "ma_rec",
        "mean": 0.6141312956809999,
        "std": 0.006418656749668427,
        "n": 5,
        "type": "predictive"
    },
    "94": {
        "step": 7,
        "metric": "mae",
        "mean": 0.3586032629013062,
        "std": 0.006101817870257843,
        "n": 5,
        "type": "predictive"
    },
    "95": {
        "step": 7,
        "metric": "meta_doa",
        "mean": 0.5045246904740194,
        "std": 0.010949881827279486,
        "n": 5,
        "type": "interpretability"
    },
    "96": {
        "step": 7,
        "metric": "mi_acc",
        "mean": 0.6413967370986939,
        "std": 0.006101820657887361,
        "n": 5,
        "type": "predictive"
    },
    "97": {
        "step": 7,
        "metric": "mi_auc",
        "mean": 0.6141313036087326,
        "std": 0.006418634395518426,
        "n": 5,
        "type": "predictive"
    },
    "98": {
        "step": 7,
        "metric": "mi_f_b",
        "mean": 0.7311799883842468,
        "std": 0.0038501087554021853,
        "n": 5,
        "type": "predictive"
    },
    "99": {
        "step": 7,
        "metric": "mi_prec",
        "mean": 0.7965976238250733,
        "std": 0.009549327250882294,
        "n": 5,
        "type": "predictive"
    },
    "100": {
        "step": 7,
        "metric": "mi_rec",
        "mean": 0.6759474515914917,
        "std": 0.007572571711172316,
        "n": 5,
        "type": "predictive"
    },
    "101": {
        "step": 7,
        "metric": "pc-er",
        "mean": 0.10918884277343748,
        "std": 0.10674242864929268,
        "n": 5,
        "type": "interpretability"
    },
    "102": {
        "step": 7,
        "metric": "rm",
        "mean": 0.10231559210279965,
        "std": 0.02513102076515299,
        "n": 5,
        "type": "interpretability"
    },
    "103": {
        "step": 7,
        "metric": "rmse",
        "mean": 0.598721730709076,
        "std": 0.004951093406556999,
        "n": 5,
        "type": "predictive"
    },
    "104": {
        "step": 8,
        "metric": "ma_f_b",
        "mean": 0.6001182198524476,
        "std": 0.010210858327194827,
        "n": 5,
        "type": "predictive"
    },
    "105": {
        "step": 8,
        "metric": "ma_prec",
        "mean": 0.599988830089569,
        "std": 0.009410850106564055,
        "n": 5,
        "type": "predictive"
    },
    "106": {
        "step": 8,
        "metric": "ma_rec",
        "mean": 0.6177911996841432,
        "std": 0.008566387261247333,
        "n": 5,
        "type": "predictive"
    },
    "107": {
        "step": 8,
        "metric": "mae",
        "mean": 0.35580810308456423,
        "std": 0.007874273652124708,
        "n": 5,
        "type": "predictive"
    },
    "108": {
        "step": 8,
        "metric": "meta_doa",
        "mean": 0.5087862113132312,
        "std": 0.010402341731726963,
        "n": 5,
        "type": "interpretability"
    },
    "109": {
        "step": 8,
        "metric": "mi_acc",
        "mean": 0.644191884994507,
        "std": 0.007874273211890458,
        "n": 5,
        "type": "predictive"
    },
    "110": {
        "step": 8,
        "metric": "mi_auc",
        "mean": 0.6177912092276957,
        "std": 0.00856634823210948,
        "n": 5,
        "type": "predictive"
    },
    "111": {
        "step": 8,
        "metric": "mi_f_b",
        "mean": 0.7325272917747497,
        "std": 0.005668891408573573,
        "n": 5,
        "type": "predictive"
    },
    "112": {
        "step": 8,
        "metric": "mi_prec",
        "mean": 0.7960156083106995,
        "std": 0.011837212262198577,
        "n": 5,
        "type": "predictive"
    },
    "113": {
        "step": 8,
        "metric": "mi_rec",
        "mean": 0.678698742389679,
        "std": 0.00839057030380886,
        "n": 5,
        "type": "predictive"
    },
    "114": {
        "step": 8,
        "metric": "pc-er",
        "mean": 0.11392822265624998,
        "std": 0.10144087331149237,
        "n": 5,
        "type": "interpretability"
    },
    "115": {
        "step": 8,
        "metric": "rm",
        "mean": 0.11855834771173908,
        "std": 0.02467191809560775,
        "n": 5,
        "type": "interpretability"
    },
    "116": {
        "step": 8,
        "metric": "rmse",
        "mean": 0.5963455200195313,
        "std": 0.006338162433850805,
        "n": 5,
        "type": "predictive"
    },
    "117": {
        "step": 9,
        "metric": "ma_f_b",
        "mean": 0.6068211078643799,
        "std": 0.009323128648647113,
        "n": 5,
        "type": "predictive"
    },
    "118": {
        "step": 9,
        "metric": "ma_prec",
        "mean": 0.6061073660850524,
        "std": 0.008756051721681328,
        "n": 5,
        "type": "predictive"
    },
    "119": {
        "step": 9,
        "metric": "ma_rec",
        "mean": 0.6242442607879639,
        "std": 0.008364677421503146,
        "n": 5,
        "type": "predictive"
    },
    "120": {
        "step": 9,
        "metric": "mae",
        "mean": 0.35061280131340034,
        "std": 0.007682203152649943,
        "n": 5,
        "type": "predictive"
    },
    "121": {
        "step": 9,
        "metric": "meta_doa",
        "mean": 0.5122113739289841,
        "std": 0.010173991239418676,
        "n": 5,
        "type": "interpretability"
    },
    "122": {
        "step": 9,
        "metric": "mi_acc",
        "mean": 0.6493872046470643,
        "std": 0.007682205650494526,
        "n": 5,
        "type": "predictive"
    },
    "123": {
        "step": 9,
        "metric": "mi_auc",
        "mean": 0.6242442534649806,
        "std": 0.008364643892692022,
        "n": 5,
        "type": "predictive"
    },
    "124": {
        "step": 9,
        "metric": "mi_f_b",
        "mean": 0.7357806086540222,
        "std": 0.006003589530997335,
        "n": 5,
        "type": "predictive"
    },
    "125": {
        "step": 9,
        "metric": "mi_prec",
        "mean": 0.7976815342903137,
        "std": 0.011995407625760016,
        "n": 5,
        "type": "predictive"
    },
    "126": {
        "step": 9,
        "metric": "mi_rec",
        "mean": 0.683043384552002,
        "std": 0.0076600920023659706,
        "n": 5,
        "type": "predictive"
    },
    "127": {
        "step": 9,
        "metric": "pc-er",
        "mean": 0.14290161132812498,
        "std": 0.10430033245856606,
        "n": 5,
        "type": "interpretability"
    },
    "128": {
        "step": 9,
        "metric": "rm",
        "mean": 0.1337487797401359,
        "std": 0.025069697360757016,
        "n": 5,
        "type": "interpretability"
    },
    "129": {
        "step": 9,
        "metric": "rmse",
        "mean": 0.5919805645942688,
        "std": 0.006264254782914914,
        "n": 5,
        "type": "predictive"
    },
    "130": {
        "step": 10,
        "metric": "ma_f_b",
        "mean": 0.6110247492790223,
        "std": 0.00814875476871637,
        "n": 5,
        "type": "predictive"
    },
    "131": {
        "step": 10,
        "metric": "ma_prec",
        "mean": 0.6099443674087525,
        "std": 0.007714337079053431,
        "n": 5,
        "type": "predictive"
    },
    "132": {
        "step": 10,
        "metric": "ma_rec",
        "mean": 0.6279191970825196,
        "std": 0.007325026764900235,
        "n": 5,
        "type": "predictive"
    },
    "133": {
        "step": 10,
        "metric": "mae",
        "mean": 0.3476015567779541,
        "std": 0.006728221909185229,
        "n": 5,
        "type": "predictive"
    },
    "134": {
        "step": 10,
        "metric": "meta_doa",
        "mean": 0.5152112162599445,
        "std": 0.011111943184427072,
        "n": 5,
        "type": "interpretability"
    },
    "135": {
        "step": 10,
        "metric": "mi_acc",
        "mean": 0.6523984551429749,
        "std": 0.006728230026562365,
        "n": 5,
        "type": "predictive"
    },
    "136": {
        "step": 10,
        "metric": "mi_auc",
        "mean": 0.6279192219043175,
        "std": 0.007325002792524772,
        "n": 5,
        "type": "predictive"
    },
    "137": {
        "step": 10,
        "metric": "mi_f_b",
        "mean": 0.737507677078247,
        "std": 0.005416857885707684,
        "n": 5,
        "type": "predictive"
    },
    "138": {
        "step": 10,
        "metric": "mi_prec",
        "mean": 0.7978541612625122,
        "std": 0.011760035803610954,
        "n": 5,
        "type": "predictive"
    },
    "139": {
        "step": 10,
        "metric": "mi_rec",
        "mean": 0.6858670592308045,
        "std": 0.0069741473147825715,
        "n": 5,
        "type": "predictive"
    },
    "140": {
        "step": 10,
        "metric": "pc-er",
        "mean": 0.15419921874999998,
        "std": 0.10503956395629259,
        "n": 5,
        "type": "interpretability"
    },
    "141": {
        "step": 10,
        "metric": "rm",
        "mean": 0.14775283272259365,
        "std": 0.025281909962961455,
        "n": 5,
        "type": "interpretability"
    },
    "142": {
        "step": 10,
        "metric": "rmse",
        "mean": 0.5894400954246521,
        "std": 0.005494230764285162,
        "n": 5,
        "type": "predictive"
    },
    "143": {
        "step": 11,
        "metric": "ma_f_b",
        "mean": 0.6152597784996033,
        "std": 0.006093855415440061,
        "n": 5,
        "type": "predictive"
    },
    "144": {
        "step": 11,
        "metric": "ma_prec",
        "mean": 0.6138328671455383,
        "std": 0.005662412564506131,
        "n": 5,
        "type": "predictive"
    },
    "145": {
        "step": 11,
        "metric": "ma_rec",
        "mean": 0.6313559532165528,
        "std": 0.0054123790667815206,
        "n": 5,
        "type": "predictive"
    },
    "146": {
        "step": 11,
        "metric": "mae",
        "mean": 0.34470061063766483,
        "std": 0.005002143772697768,
        "n": 5,
        "type": "predictive"
    },
    "147": {
        "step": 11,
        "metric": "meta_doa",
        "mean": 0.5181234750924724,
        "std": 0.011103154616069278,
        "n": 5,
        "type": "interpretability"
    },
    "148": {
        "step": 11,
        "metric": "mi_acc",
        "mean": 0.6552993893623353,
        "std": 0.00500214100401087,
        "n": 5,
        "type": "predictive"
    },
    "149": {
        "step": 11,
        "metric": "mi_auc",
        "mean": 0.6313559528787231,
        "std": 0.005412359505011993,
        "n": 5,
        "type": "predictive"
    },
    "150": {
        "step": 11,
        "metric": "mi_f_b",
        "mean": 0.7389739632606507,
        "std": 0.004315766580724744,
        "n": 5,
        "type": "predictive"
    },
    "151": {
        "step": 11,
        "metric": "mi_prec",
        "mean": 0.7971666336059571,
        "std": 0.010408570112771558,
        "n": 5,
        "type": "predictive"
    },
    "152": {
        "step": 11,
        "metric": "mi_rec",
        "mean": 0.6888956427574158,
        "std": 0.0053077912256191545,
        "n": 5,
        "type": "predictive"
    },
    "153": {
        "step": 11,
        "metric": "pc-er",
        "mean": 0.16314697265624997,
        "std": 0.10486169243680196,
        "n": 5,
        "type": "interpretability"
    },
    "154": {
        "step": 11,
        "metric": "rm",
        "mean": 0.15666462690956284,
        "std": 0.02364002055059407,
        "n": 5,
        "type": "interpretability"
    },
    "155": {
        "step": 11,
        "metric": "rmse",
        "mean": 0.5869877457618714,
        "std": 0.00408758367021455,
        "n": 5,
        "type": "predictive"
    },
    "156": {
        "step": 12,
        "metric": "ma_f_b",
        "mean": 0.6190591454505922,
        "std": 0.006528264393364004,
        "n": 5,
        "type": "predictive"
    },
    "157": {
        "step": 12,
        "metric": "ma_prec",
        "mean": 0.6173245429992675,
        "std": 0.006083487165672062,
        "n": 5,
        "type": "predictive"
    },
    "158": {
        "step": 12,
        "metric": "ma_rec",
        "mean": 0.6344484806060792,
        "std": 0.0063542489616841115,
        "n": 5,
        "type": "predictive"
    },
    "159": {
        "step": 12,
        "metric": "mae",
        "mean": 0.3421069741249085,
        "std": 0.005648833644193414,
        "n": 5,
        "type": "predictive"
    },
    "160": {
        "step": 12,
        "metric": "meta_doa",
        "mean": 0.5209536607613978,
        "std": 0.011036871074510337,
        "n": 5,
        "type": "interpretability"
    },
    "161": {
        "step": 12,
        "metric": "mi_acc",
        "mean": 0.6578930139541627,
        "std": 0.005648823398111475,
        "n": 5,
        "type": "predictive"
    },
    "162": {
        "step": 12,
        "metric": "mi_auc",
        "mean": 0.6344484800067491,
        "std": 0.00635426017895352,
        "n": 5,
        "type": "predictive"
    },
    "163": {
        "step": 12,
        "metric": "mi_f_b",
        "mean": 0.7402037143707275,
        "std": 0.005277130804993444,
        "n": 5,
        "type": "predictive"
    },
    "164": {
        "step": 12,
        "metric": "mi_prec",
        "mean": 0.7962906360626221,
        "std": 0.011905082375954541,
        "n": 5,
        "type": "predictive"
    },
    "165": {
        "step": 12,
        "metric": "mi_rec",
        "mean": 0.6916792631149292,
        "std": 0.005057069147078017,
        "n": 5,
        "type": "predictive"
    },
    "166": {
        "step": 12,
        "metric": "pc-er",
        "mean": 0.17267456054687497,
        "std": 0.10383735466457053,
        "n": 5,
        "type": "interpretability"
    },
    "167": {
        "step": 12,
        "metric": "rm",
        "mean": 0.1709468288088954,
        "std": 0.022663110472193455,
        "n": 5,
        "type": "interpretability"
    },
    "168": {
        "step": 12,
        "metric": "rmse",
        "mean": 0.5847895741462709,
        "std": 0.004820811205148856,
        "n": 5,
        "type": "predictive"
    },
    "169": {
        "step": 13,
        "metric": "ma_f_b",
        "mean": 0.6236160635948182,
        "std": 0.009767246072311322,
        "n": 5,
        "type": "predictive"
    },
    "170": {
        "step": 13,
        "metric": "ma_prec",
        "mean": 0.6215710639953613,
        "std": 0.009228102711696978,
        "n": 5,
        "type": "predictive"
    },
    "171": {
        "step": 13,
        "metric": "ma_rec",
        "mean": 0.6383583188056947,
        "std": 0.010410026035946358,
        "n": 5,
        "type": "predictive"
    },
    "172": {
        "step": 13,
        "metric": "mae",
        "mean": 0.33879049420356755,
        "std": 0.00889800262367346,
        "n": 5,
        "type": "predictive"
    },
    "173": {
        "step": 13,
        "metric": "meta_doa",
        "mean": 0.5232017044855446,
        "std": 0.010849354778233015,
        "n": 5,
        "type": "interpretability"
    },
    "174": {
        "step": 13,
        "metric": "mi_acc",
        "mean": 0.6612094998359681,
        "std": 0.008898006336033795,
        "n": 5,
        "type": "predictive"
    },
    "175": {
        "step": 13,
        "metric": "mi_auc",
        "mean": 0.6383583299574827,
        "std": 0.01041001181466127,
        "n": 5,
        "type": "predictive"
    },
    "176": {
        "step": 13,
        "metric": "mi_f_b",
        "mean": 0.7420832514762878,
        "std": 0.007483838051573905,
        "n": 5,
        "type": "predictive"
    },
    "177": {
        "step": 13,
        "metric": "mi_prec",
        "mean": 0.7962915182113648,
        "std": 0.012696447714638766,
        "n": 5,
        "type": "predictive"
    },
    "178": {
        "step": 13,
        "metric": "mi_rec",
        "mean": 0.6949365615844727,
        "std": 0.006623720423990434,
        "n": 5,
        "type": "predictive"
    },
    "179": {
        "step": 13,
        "metric": "pc-er",
        "mean": 0.19108886718749998,
        "std": 0.09703324990046706,
        "n": 5,
        "type": "interpretability"
    },
    "180": {
        "step": 13,
        "metric": "rm",
        "mean": 0.18385619828444616,
        "std": 0.022027289305152648,
        "n": 5,
        "type": "interpretability"
    },
    "181": {
        "step": 13,
        "metric": "rmse",
        "mean": 0.5819185495376588,
        "std": 0.007667485288383821,
        "n": 5,
        "type": "predictive"
    },
    "182": {
        "step": 14,
        "metric": "ma_f_b",
        "mean": 0.6267738580703737,
        "std": 0.008861933126324892,
        "n": 5,
        "type": "predictive"
    },
    "183": {
        "step": 14,
        "metric": "ma_prec",
        "mean": 0.6245051264762879,
        "std": 0.008436839300915452,
        "n": 5,
        "type": "predictive"
    },
    "184": {
        "step": 14,
        "metric": "ma_rec",
        "mean": 0.6408322453498841,
        "std": 0.009536597196803014,
        "n": 5,
        "type": "predictive"
    },
    "185": {
        "step": 14,
        "metric": "mae",
        "mean": 0.336704558134079,
        "std": 0.008195754030924107,
        "n": 5,
        "type": "predictive"
    },
    "186": {
        "step": 14,
        "metric": "meta_doa",
        "mean": 0.5247145957463095,
        "std": 0.010818917462603505,
        "n": 5,
        "type": "interpretability"
    },
    "187": {
        "step": 14,
        "metric": "mi_acc",
        "mean": 0.6632954239845277,
        "std": 0.008195756604039503,
        "n": 5,
        "type": "predictive"
    },
    "188": {
        "step": 14,
        "metric": "mi_auc",
        "mean": 0.6408322492245497,
        "std": 0.009536601215906921,
        "n": 5,
        "type": "predictive"
    },
    "189": {
        "step": 14,
        "metric": "mi_f_b",
        "mean": 0.743006682395935,
        "std": 0.007115962961703516,
        "n": 5,
        "type": "predictive"
    },
    "190": {
        "step": 14,
        "metric": "mi_prec",
        "mean": 0.7952690124511719,
        "std": 0.012639184782664271,
        "n": 5,
        "type": "predictive"
    },
    "191": {
        "step": 14,
        "metric": "mi_rec",
        "mean": 0.697323226928711,
        "std": 0.006123571118833925,
        "n": 5,
        "type": "predictive"
    },
    "192": {
        "step": 14,
        "metric": "pc-er",
        "mean": 0.2009521484375,
        "std": 0.09783287859805048,
        "n": 5,
        "type": "interpretability"
    },
    "193": {
        "step": 14,
        "metric": "rm",
        "mean": 0.19629659998790477,
        "std": 0.021812132990460437,
        "n": 5,
        "type": "interpretability"
    },
    "194": {
        "step": 14,
        "metric": "rmse",
        "mean": 0.5801411390304566,
        "std": 0.007060600384760164,
        "n": 5,
        "type": "predictive"
    },
    "195": {
        "step": 15,
        "metric": "ma_f_b",
        "mean": 0.6292160272598267,
        "std": 0.009340826309796164,
        "n": 5,
        "type": "predictive"
    },
    "196": {
        "step": 15,
        "metric": "ma_prec",
        "mean": 0.6268195390701294,
        "std": 0.008854938281767323,
        "n": 5,
        "type": "predictive"
    },
    "197": {
        "step": 15,
        "metric": "ma_rec",
        "mean": 0.6428197026252748,
        "std": 0.009492032665627372,
        "n": 5,
        "type": "predictive"
    },
    "198": {
        "step": 15,
        "metric": "mae",
        "mean": 0.3350447535514832,
        "std": 0.008202116978410006,
        "n": 5,
        "type": "predictive"
    },
    "199": {
        "step": 15,
        "metric": "meta_doa",
        "mean": 0.5272967314056454,
        "std": 0.010728643524012465,
        "n": 5,
        "type": "interpretability"
    },
    "200": {
        "step": 15,
        "metric": "mi_acc",
        "mean": 0.664955234527588,
        "std": 0.008202122912152074,
        "n": 5,
        "type": "predictive"
    },
    "201": {
        "step": 15,
        "metric": "mi_auc",
        "mean": 0.6428197101978302,
        "std": 0.00949203802735814,
        "n": 5,
        "type": "predictive"
    },
    "202": {
        "step": 15,
        "metric": "mi_f_b",
        "mean": 0.7437646269798279,
        "std": 0.007026116404344352,
        "n": 5,
        "type": "predictive"
    },
    "203": {
        "step": 15,
        "metric": "mi_prec",
        "mean": 0.7945577383041382,
        "std": 0.013333782656160352,
        "n": 5,
        "type": "predictive"
    },
    "204": {
        "step": 15,
        "metric": "mi_rec",
        "mean": 0.6992203712463378,
        "std": 0.006714711750505018,
        "n": 5,
        "type": "predictive"
    },
    "205": {
        "step": 15,
        "metric": "pc-er",
        "mean": 0.20859375,
        "std": 0.08109981154056577,
        "n": 5,
        "type": "interpretability"
    },
    "206": {
        "step": 15,
        "metric": "rm",
        "mean": 0.20743763121397887,
        "std": 0.021654688851346558,
        "n": 5,
        "type": "interpretability"
    },
    "207": {
        "step": 15,
        "metric": "rmse",
        "mean": 0.5787054419517518,
        "std": 0.0070922958540285625,
        "n": 5,
        "type": "predictive"
    }
}